iloveapi-1.0.0.dist-info/METADATA
iloveapi-1.0.0.dist-info/WHEEL
iloveapi-1.0.0.dist-info/entry_points.txt
iloveapi-1.0.0.dist-info/licenses/LICENSE
iloveapi/__init__.py
iloveapi/auth.py
iloveapi/iloveapi.py
iloveapi/rest.py
iloveapi/task.py
iloveapi/typing.py
iloveapi/utils.py
iloveapi-1.0.0.dist-info/RECORD
