Metadata-Version: 2.1
Name: iloveapi
Version: 1.0.0
Summary: Python api client made for iLoveIMG & iLovePDF based on iLoveAPI (https://www.iloveapi.com/docs/api-reference).
Keywords: iloveapi,iloveimg,ilovepdf,api,sdk,client
Author-Email: iyume <iyumelive@gmail.com>
License: MIT
Project-URL: homepage, https://github.com/iyume/iloveapi-python
Project-URL: repository, https://github.com/iyume/iloveapi-python.git
Requires-Python: >=3.9
Requires-Dist: typing-extensions>=4.0
Requires-Dist: httpx>=0.26.0
Requires-Dist: pyjwt>=2.4.0
